restart_crossdomain/cors.py
restart_crossdomain/__init__.py
RESTArt_CrossDomain-0.1.2.dist-info/WHEEL
RESTArt_CrossDomain-0.1.2.dist-info/RECORD
RESTArt_CrossDomain-0.1.2.dist-info/METADATA
RESTArt_CrossDomain-0.1.2.dist-info/metadata.json
RESTArt_CrossDomain-0.1.2.dist-info/top_level.txt
RESTArt_CrossDomain-0.1.2.dist-info/DESCRIPTION.rst
