Metadata-Version: 2.0
Name: RESTArt-CrossDomain
Version: 0.1.2
Summary: A RESTArt extension for cross-domain access.
Home-page: https://github.com/RussellLuo/restart-crossdomain
Author: RussellLuo
Author-email: luopeng.he@gmail.com
License: MIT
Keywords: Cross-domain access,CORS,RESTArt,Python
Platform: UNKNOWN
